setup.py
siddhi_indian_states_25/__init__.py
siddhi_indian_states_25/asgi.py
siddhi_indian_states_25/settings.py
siddhi_indian_states_25/urls.py
siddhi_indian_states_25/wsgi.py
siddhi_indian_states_25.egg-info/PKG-INFO
siddhi_indian_states_25.egg-info/SOURCES.txt
siddhi_indian_states_25.egg-info/dependency_links.txt
siddhi_indian_states_25.egg-info/requires.txt
siddhi_indian_states_25.egg-info/top_level.txt
sst1/__init__.py
sst1/admin.py
sst1/apps.py
sst1/fields.py
sst1/forms.py
sst1/models.py
sst1/states.py
sst1/tests.py
sst1/views.py
sst1/migrations/__init__.py